{
  "project_info": {
    "project_number": "227921749731",
    "firebase_url": "https://studentmanagement-eaec6-default-rtdb.firebaseio.com",
    "project_id": "studentmanagement-eaec6",
    "storage_bucket": "studentmanagement-eaec6.appspot.com"
  },
  "client": [
    {
      "client_info": {
        "mobilesdk_app_id": "1:227921749731:android:e633cddc30c2a27d18c7d6",
        "android_client_info": {
          "package_name": "com.example.aadminpanel"
        }
      },
      "oauth_client": [],
      "api_key": [
        {
          "current_key": "AIzaSyBZpT5KT3-C1OgsDdbnKq20tdfK0OcoXIA"
        }
      ],
      "services": {
        "appinvite_service": {
          "other_platform_oauth_client": []
        }
      }
    },
    {
      "client_info": {
        "mobilesdk_app_id": "1:227921749731:android:5dc5e82788240f1e18c7d6",
        "android_client_info": {
          "package_name": "com.example.studentmanagement"
        }
      },
      "oauth_client": [],
      "api_key": [
        {
          "current_key": "AIzaSyBZpT5KT3-C1OgsDdbnKq20tdfK0OcoXIA"
        }
      ],
      "services": {
        "appinvite_service": {
          "other_platform_oauth_client": []
        }
      }
    }
  ],
  "configuration_version": "1"
}